useful_functions_easier_life/LICENSE
useful_functions_easier_life/README.MD
useful_functions_easier_life/__init__.py
useful_functions_easier_life/requirements.txt
useful_functions_easier_life/thirdparty.json
useful_functions_easier_life-0.14.dist-info/LICENSE.rst
useful_functions_easier_life-0.14.dist-info/METADATA
useful_functions_easier_life-0.14.dist-info/WHEEL
useful_functions_easier_life-0.14.dist-info/top_level.txt
useful_functions_easier_life-0.14.dist-info/RECORD
